jax/geneweaver/db/__init__.py
jax/geneweaver/db/annotator.py
jax/geneweaver/db/gene.py
jax/geneweaver/db/geneset/__init__.py
jax/geneweaver/db/geneset/create.py
jax/geneweaver/db/publication.py
jax/geneweaver/db/sql/__init__.py
jax/geneweaver/db/sql/geneset.py
jax/geneweaver/db/sql/publication.py
jax/geneweaver/db/sql/user.py
jax/geneweaver/db/user.py
jax_geneweaver_db-0.0.1.dist-info/WHEEL
jax_geneweaver_db-0.0.1.dist-info/METADATA
jax_geneweaver_db-0.0.1.dist-info/RECORD
