Metadata-Version: 2.1
Name: jax-geneweaver-db
Version: 0.0.1
Summary: 
Author: Jax & Baylor Computational Sciences
Author-email: cssc@jax.org
Requires-Python: >=3.9,<4.0
Classifier: Programming Language :: Python :: 3
Classifier: Programming Language :: Python :: 3.9
Classifier: Programming Language :: Python :: 3.10
Classifier: Programming Language :: Python :: 3.11
Requires-Dist: jax-geneweaver-core (>=0.0.5,<0.0.6)
Requires-Dist: psycopg2-binary (>=2.9.5,<3.0.0)
